<?xml version="1.0" encoding="utf-8"?>
<Level width="3">
  <Camera x="0" y="5" minWidth="20" maxWidth="40" />
  <Birds>
    <Bird type="BirdRed" />
    <Bird type="BirdBlack" />
    <Bird type="BirdWhite" />
  </Birds>
  <Slingshot x="-15" y="-2.5" />
  <GameObjects>
    <Block type="RectBig" material="wood" x="4.999944" y="-3.376021" rotation="-0.005003441" id="0" aVelocity="0.001658468" />
    <Block type="RectTiny" material="wood" x="4.101016" y="-3.036987" rotation="89.958" id="1" aVelocity="0.04281311" />
    <Block type="RectTiny" material="wood" x="5.899198" y="-3.037644" rotation="89.93236" id="2" aVelocity="0.04325301" />
    <Block type="RectBig" material="wood" x="4.99806" y="-2.698676" rotation="-0.03672902" id="3" aVelocity="0.0920582" />
    <Block type="RectBig" material="wood" x="2.498836" y="-3.376928" rotation="-0.008804402" id="4" aVelocity="0.004897654" />
    <Block type="RectTiny" material="wood" x="1.597395" y="-3.03887" rotation="89.94278" id="5" aVelocity="0.07449348" />
    <Block type="RectTiny" material="wood" x="3.371068" y="-3.040096" rotation="89.86904" id="6" aVelocity="0.08918621" />
    <Block type="RectBig" material="wood" x="2.500379" y="-2.702331" rotation="-0.0722593" id="7" aVelocity="0.1828467" />
    <Block type="RectMedium" material="wood" x="2.507497" y="-1.737881" rotation="89.68558" id="8" aVelocity="1.278824" />
    <Block type="RectMedium" material="wood" x="1.623314" y="-1.734577" rotation="88.73878" id="9" aVelocity="1.386885" />
    <Block type="RectMedium" material="wood" x="3.635843" y="-1.987195" rotation="27.62433" id="10" aVelocity="26.93503" />
    <Block type="RectBig" material="wood" x="2.536025" y="-0.7718623" rotation="-1.641585" id="11" aVelocity="2.438982" />
    <Block type="RectBig" material="wood" x="0.003959344" y="-3.37512" rotation="0.0005022757" id="12" aVelocity="0.06530763" />
    <Block type="RectBig" material="wood" x="-3.58683" y="-2.826091" rotation="18.1207" id="24" aVelocity="0.4004222" />
    <Block type="RectSmall" material="wood" x="-2.500035" y="-3.059459" rotation="91.28546" id="25" aVelocity="1.135931" />
    <Block type="RectBig" material="wood" x="-4.998466" y="-3.375082" rotation="0.002830412" id="37" aVelocity="0.03666971" />
    <Block type="RectTiny" material="wood" x="-5.899989" y="-3.035269" rotation="89.96649" id="38" aVelocity="0.3736904" />
    <Block type="RectTiny" material="wood" x="-4.823864" y="-3.120793" rotation="5.279655" id="39" aVelocity="10.79573" />
    <Block type="RectBig" material="wood" x="-4.994852" y="-2.702893" rotation="-0.5103875" id="40" aVelocity="0.6060631" />
    <Block type="RectBig" material="wood" x="-5.001778" y="-2.472575" rotation="-0.6203465" id="41" aVelocity="0.9445407" />
    <Block type="RectMedium" material="wood" x="-7.518412" y="-2.642279" rotation="91.08306" id="49" aVelocity="5.371219" />
    <Block type="RectMedium" material="wood" x="-9.408891" y="-3.375371" rotation="180.0021" id="50" aVelocity="72.74147" />
    <Block type="RectMedium" material="wood" x="-6.616716" y="-2.642232" rotation="91.0265" id="51" aVelocity="5.463454" />
    <Block type="RectMedium" material="wood" x="7.499982" y="-2.644957" rotation="89.95638" id="53" aVelocity="3.40469" />
    <Block type="RectMedium" material="wood" x="6.804247" y="-2.644791" rotation="90.20267" id="54" aVelocity="3.40469" />
    <Block type="RectMedium" material="wood" x="8.399994" y="-2.645017" rotation="89.99773" id="55" aVelocity="3.40469" />
    <Block type="RectBig" material="wood" x="7.500093" y="-1.679872" rotation="-0.01369312" id="56" aVelocity="3.40469" />
    <Block type="RectBig" material="wood" x="5.866421" y="-2.245609" rotation="-45.64375" id="57" aVelocity="10.37686" />
    <Block type="RectBig" material="wood" x="4.107604" y="-2.00499" rotation="27.61331" id="58" aVelocity="1.64722" />
    <Block type="RectSmall" material="wood" x="5.021441" y="-2.149056" rotation="89.72157" id="59" aVelocity="2.85502" />
    <Block type="RectMedium" material="wood" x="1.652875" y="0.2194519" rotation="88.95577" id="60" aVelocity="4.006469" />
    <Block type="RectMedium" material="wood" x="3.451253" y="0.1669583" rotation="88.46546" id="61" aVelocity="5.330628" />
    <Block type="RectBig" material="wood" x="2.587066" y="1.159776" rotation="-1.665742" id="62" aVelocity="5.439016" />
  </GameObjects>
</Level>
