<?xml version="1.0" encoding="utf-8"?>
<Level width="3">
  <Camera x="0" y="5" minWidth="20" maxWidth="40" />
  <Birds>
    <Bird type="BirdRed" />
    <Bird type="BirdBlack" />
    <Bird type="BirdWhite" />
  </Birds>
  <Slingshot x="-15" y="-2.5" />
  <GameObjects>
    <Block type="SquareHole" material="wood" x="0.0001633842" y="-3.064852" rotation="-0.0201467" id="11" aVelocity="0.08983897" />
    <Block type="RectTiny" material="wood" x="-0.0001189018" y="-2.51753" rotation="-0.4556277" id="12" aVelocity="3.398064" />
    <Block type="TriangleHole" material="wood" x="-2.41927" y="-3.065002" rotation="0.0001781825" id="20" aVelocity="0.04367049" />
    <Block type="RectTiny" material="wood" x="-4.987003" y="-3.377892" rotation="0.09465999" id="33" aVelocity="0.0001247975" />
    <Block type="SquareSmall" material="wood" x="-4.993976" y="-2.579123" rotation="0.07813159" id="34" aVelocity="0.001064961" />
    <Block type="RectTiny" material="wood" x="-7.490491" y="-2.919031" rotation="-0.06771491" id="35" aVelocity="0.0001787162" />
    <Block type="RectSmall" material="wood" x="-7.499973" y="-2.689957" rotation="-0.07331862" id="36" aVelocity="0.1926267" />
    <Pig type="BasicSmall" x="5" y="-3.4" rotation="0" id="37" aVelocity="32.14961" />
    <Pig type="BasicSmall" x="-5" y="-3.15" rotation="0" id="41" aVelocity="0.0004781843" />
    <Pig type="BasicSmall" x="-7.5" y="-3.4" rotation="0" id="42" aVelocity="8.012063E-05" />
  </GameObjects>
</Level>
